{
  "id": "exp_c678161b52da2a03",
  "query": "Объясни: Что ты предложишь в качестве мер для развития ИИ в России?",
  "response": "несколько возможных шагов, которые можно принять по развитию искусственного интеллекта (ИИ) во всемирной Федерации:\n\n1. Создание государственной стратегии ИИ - это позволит сосредоточиться на ключевых областях развития и обеспечит координацию усилий различных ведомств.\n\n2 Реализация программ обучения для студентов по искусственному интеллекту, чтобы повысить уровень квалификации специалиста. \n\n3 Создание центров исследоания ИИ - это позволит проводим научные исследования и разработки новых технологий в области ИИ.\n\n4 Поддержка открытых данных для обучения машинного кодирования – доступность информации может помочь улучшить качество программных продуктов, которые используются всем миром. \n\n5 Учрежденение конкурсов на лучшие решения ИИ - это способ привлечения внимания к проблемам и вызову в области ИИ.\n\n6 Поддержка инновационного бизнеса по искусственному Интеллекте – создание условий для развития новых компаний, которые используют технологии Искусственного Разума. \n\n7 Создайте программное обеспечение ИИ - это способ обеспечить доступность технологиям большего числу людей и организаций.\n\nЭти шаги могут помочь России стать одним из лидеров в области искусственных интеллекта во всем мире, но важно также учиться у других стран по этому вопросу.",
  "model_used": "model_b",
  "quality_score": 0.8,
  "embedding": [],
  "tags": [],
  "timestamp": 1775464079.3477795,
  "usage_count": 0,
  "related_experiences": []
}
