{
  "id": "exp_316f7510a6ecec7d",
  "query": "Объясни: Привет!",
  "response": "Просто присутствие \"прива\" в начале фразы делает его более informal (неформальным) и дружелюбным, как если бы кто-то сказал тебе просто здравствуй. Это выражение часто используется для начала разговора или сообщения с целью установления теплого контакта.\n\nВаш вариант \"Привет!\" является коротким присоединением к встрече и также может быть использован в разных контекстах, от простой знакомки до более формальных ситуаций.",
  "model_used": "model_b",
  "quality_score": 0.8,
  "embedding": [],
  "tags": [],
  "timestamp": 1775212872.7488887,
  "usage_count": 23,
  "related_experiences": []
}