{
  "id": "exp_f874ef874dc8a616",
  "query": "В период властвования Екатерины II были осуществлены глубокие преобразования в сфере управления, экономики, финансов и культуры, сопоставимые по масштабам и значению с реформами Петра Великого. Деятельность Екатерины II была направлена на развитие, закрепление и корректировку того курса, которым шла страна с начала века. Большое значение для Екатерины II имели идеи Просвещения, популярные среди большинства европейских монархов.\n\nПравление Екатерины II сопровождалось расширением прав дворянства, сохранением и развитием крепостнической системы. Восстание Емельяна Пугачёва заставило скорректировать прежнюю политику как по направлению к централизации государства, так и в сторону предоставления свобод торговому и городскому сословию.\n\nВо второй половине XVIII в. Российская империя превратилась в ещё более могущественным и влиятельным участником европейской и мировой политики . Серия военных побед и крупных внешнеполитических успехов привела к существенному расширению российских владений. Россия решила исторические задачи: собрала почти всё территориальное наследие государства Русь и получила выход к Чёрному морю.\n\nМощный импульс получило развитие отечественной культуры. Приумножилось число выдающихся мастеров, прославивших себя в литературе, живописи, архитектуре, скульптуре, музыке, театре. Среди них было немало выходцев из стран Европы, внёсших неоценимый вклад в развитие российской культуры. Развивались общественная мысль и публицистика, откликавшиеся на важные социальные проблемы, среди прочих тем впервые был затронут крестьянский вопрос.\n\nНедолгое правление императора Павла сопровождалось укреплением абсолютизма, стремлением ограничить привилегии дворянства, а также активным участием России в общеевропейских событиях, связанных с революционными войнами Франции.",
  "response": "В период правления Екатерины II произошли значительные преобразования в различных сферах жизни России:\nПолитические реформы: Расширение прав дворянства и сохранение крепостнической системы были ключевыми мерами. Эти изменения помогли укрепить государственную систему, хотя они также способствовали ограничению свобод торговому сословию.\nЭкономическая модернизация: Реформы Екатерины II направлены на развитие и корректировку экономической системы России в соответствии с идеями просвещения. Это позволило сделать страну более конкурентоспособной мировым рынкам, что привело к значительному экономическому росту.\nФинансовые преобразования: Екатерины II удалось создать эффективную финансовую систему для управления государственным бюджетом и обеспечить стабильность экономики страны. Это способствовало развитию банковской системы России, что было особенно важно в условиях быстро меняющегося мира XVIII века.\nКультурные изменения: В культурной сфере произошли значительные преобразования благодаря усилиям Екатерины II и ее дворянства. Россия стала активным участником мирового искусства XIX столетия, привлекая таланты из других стран для работы в России.\nРазвитие отечественной культуры: В культурной сфере произошло значительное развитие благодаря усилиям Екатерины II и ее дворянства. Россия стала активным участником мирового искусства XIX столетия, привлекая таланты из других стран для работы в России.\nРазвитие общественной мысли: Важно отметить роль развития российской культуры среди выходцев из европейских государств и прославления мастеров различных искусств. Это способствовало развитию публицистики, которая откликалась на социальные проблемы страны впервые затронувшие крестьянский вопрос.\nВажным фактором стало расширение российского влияния во внешней политике благодаря серии успешных побед и крупномасштабному развитию территории России. Россия стала влиятельной участницей мировой политики, собрав почти всё территориальное наследие государства Русь.\nВажно отметить роль Екатерины II как активного игрока в общеевропейских событиях и революционных войнах Франции. Эти события способствовали расширению Российской империи, что было важно для дальнейшего развития страны на мировой арене.\nТаким образом, правление Екатерины II стало важным этапом в истории России и ее становления как мощного участника европейской политики. Эти преобразования оказали значительное влияние не только экономической жизни государства, но также культурной и общественной мысли страны.",
  "model_used": "web_ui",
  "quality_score": 0.5,
  "embedding": [],
  "tags": [],
  "timestamp": 1775722849.43429,
  "usage_count": 0,
  "related_experiences": []
}