{
  "id": "exp_6ae4a6a1c0ee53d3",
  "query": "Объясни: Привет, Ева!",
  "response": "Ваше сообщение \"Привет, Еva!\" кажется корректным и понятно сформulated пользователем в попытке приветствовать другого человека по имени Эвелина (Ева). \n\nСлово 'привет' обычно используется как формальное или informal выражения уважительного отношения к кому-либо, особенно при знакомстве. Оно также может означать \"здарова\" в более casual контексте.\n\nИмя Ева часто используетсье во многих культурах и языках мира: еврейское имя (используется для девочек), арабическое эхо имени Eve, из Библия. \n\nТаким образом ваша фраза может быть трактована как формальное приветствие или casual обращение к девушке по имени Ева.\n\nЕсли вы имели в виду что-то конкретное и хотите более точного объяснения - пожалуйста, укажите дополнительную информацию.",
  "model_used": "model_a",
  "quality_score": 0.8,
  "embedding": [],
  "tags": [],
  "timestamp": 1775374414.1172113,
  "usage_count": 0,
  "related_experiences": []
}