[
  {
    "timestamp": "2026-03-12 23:02:07",
    "total": 15.715,
    "used": 11.086,
    "free": 4.629,
    "cache": 0.0
  },
  {
    "timestamp": "2026-03-12 23:02:12",
    "total": 15.715,
    "used": 11.077,
    "free": 4.637,
    "cache": 0.0
  },
  {
    "timestamp": "2026-03-12 23:02:17",
    "total": 15.715,
    "used": 11.06,
    "free": 4.654,
    "cache": 0.0
  },
  {
    "timestamp": "2026-03-12 23:02:22",
    "total": 15.715,
    "used": 10.99,
    "free": 4.725,
    "cache": 0.0
  },
  {
    "timestamp": "2026-03-12 23:02:27",
    "total": 15.715,
    "used": 10.92,
    "free": 4.795,
    "cache": 0.0
  },
  {
    "timestamp": "2026-03-12 23:02:28",
    "total": 15.715,
    "used": 10.916,
    "free": 4.799,
    "cache": 0.0
  },
  {
    "timestamp": "2026-03-12 23:02:32",
    "total": 15.715,
    "used": 10.918,
    "free": 4.797,
    "cache": 0.0
  },
  {
    "timestamp": "2026-03-12 23:02:33",
    "total": 15.715,
    "used": 10.92,
    "free": 4.795,
    "cache": 0.0
  },
  {
    "timestamp": "2026-03-12 23:02:38",
    "total": 15.715,
    "used": 10.911,
    "free": 4.804,
    "cache": 0.0
  },
  {
    "timestamp": "2026-03-12 23:02:43",
    "total": 15.715,
    "used": 10.918,
    "free": 4.797,
    "cache": 0.0
  },
  {
    "timestamp": "2026-03-15 19:27:44",
    "total": 15.715,
    "used": 13.079,
    "free": 2.636,
    "cache": 0.0
  },
  {
    "timestamp": "2026-03-15 19:27:47",
    "total": 15.715,
    "used": 13.069,
    "free": 2.646,
    "cache": 0.0
  },
  {
    "timestamp": "2026-03-15 19:27:49",
    "total": 15.715,
    "used": 13.026,
    "free": 2.688,
    "cache": 0.0
  },
  {
    "timestamp": "2026-03-15 19:27:54",
    "total": 15.715,
    "used": 13.01,
    "free": 2.705,
    "cache": 0.0
  },
  {
    "timestamp": "2026-03-17 00:23:09",
    "total": 15.715,
    "used": 13.837,
    "free": 1.878,
    "cache": 0.0
  },
  {
    "timestamp": "2026-03-17 00:23:14",
    "total": 15.715,
    "used": 13.843,
    "free": 1.871,
    "cache": 0.0
  },
  {
    "timestamp": "2026-03-17 00:23:18",
    "total": 15.715,
    "used": 13.837,
    "free": 1.878,
    "cache": 0.0
  },
  {
    "timestamp": "2026-03-17 00:23:19",
    "total": 15.715,
    "used": 13.837,
    "free": 1.878,
    "cache": 0.0
  },
  {
    "timestamp": "2026-03-17 00:23:24",
    "total": 15.715,
    "used": 13.836,
    "free": 1.879,
    "cache": 0.0
  },
  {
    "timestamp": "2026-03-17 00:23:29",
    "total": 15.715,
    "used": 13.837,
    "free": 1.878,
    "cache": 0.0
  },
  {
    "timestamp": "2026-03-17 00:23:34",
    "total": 15.715,
    "used": 13.839,
    "free": 1.876,
    "cache": 0.0
  },
  {
    "timestamp": "2026-03-17 00:23:39",
    "total": 15.715,
    "used": 13.838,
    "free": 1.876,
    "cache": 0.0
  },
  {
    "timestamp": "2026-03-17 00:23:44",
    "total": 15.715,
    "used": 13.835,
    "free": 1.88,
    "cache": 0.0
  },
  {
    "timestamp": "2026-03-17 00:23:49",
    "total": 15.715,
    "used": 13.832,
    "free": 1.882,
    "cache": 0.0
  },
  {
    "timestamp": "2026-03-17 00:23:54",
    "total": 15.715,
    "used": 13.831,
    "free": 1.884,
    "cache": 0.0
  },
  {
    "timestamp": "2026-03-17 00:23:59",
    "total": 15.715,
    "used": 13.832,
    "free": 1.883,
    "cache": 0.0
  },
  {
    "timestamp": "2026-03-17 00:24:04",
    "total": 15.715,
    "used": 13.843,
    "free": 1.871,
    "cache": 0.0
  },
  {
    "timestamp": "2026-03-17 00:24:10",
    "total": 15.715,
    "used": 13.88,
    "free": 1.835,
    "cache": 0.0
  },
  {
    "timestamp": "2026-03-17 10:15:16",
    "total": 15.715,
    "used": 13.916,
    "free": 1.799,
    "cache": 0.0
  },
  {
    "timestamp": "2026-03-17 10:15:21",
    "total": 15.715,
    "used": 13.924,
    "free": 1.791,
    "cache": 0.0
  },
  {
    "timestamp": "2026-03-17 11:13:02",
    "total": 15.715,
    "used": 14.795,
    "free": 0.919,
    "cache": 0.0
  },
  {
    "timestamp": "2026-03-17 11:14:12",
    "total": 15.715,
    "used": 14.585,
    "free": 1.13,
    "cache": 0.0
  },
  {
    "timestamp": "2026-03-17 11:50:03",
    "total": 15.715,
    "used": 12.093,
    "free": 3.621,
    "cache": 0.0
  },
  {
    "timestamp": "2026-03-17 12:05:19",
    "total": 15.715,
    "used": 14.387,
    "free": 1.328,
    "cache": 0.0
  },
  {
    "timestamp": "2026-03-17 22:40:01",
    "total": 15.715,
    "used": 15.333,
    "free": 0.382,
    "cache": 0.0
  },
  {
    "timestamp": "2026-03-17 23:30:25",
    "total": 15.715,
    "used": 15.22,
    "free": 0.495,
    "cache": 0.0
  },
  {
    "timestamp": "2026-03-17 23:30:27",
    "total": 15.715,
    "used": 15.074,
    "free": 0.641,
    "cache": 0.0
  },
  {
    "timestamp": "2026-03-19 23:52:23",
    "total": 15.715,
    "used": 11.866,
    "free": 3.849,
    "cache": 0.0
  },
  {
    "timestamp": "2026-03-27 19:44:10",
    "total": 15.715,
    "used": 13.193,
    "free": 2.522,
    "cache": 0.0
  },
  {
    "timestamp": "2026-03-27 19:44:15",
    "total": 15.715,
    "used": 13.22,
    "free": 2.495,
    "cache": 0.0
  },
  {
    "timestamp": "2026-03-27 19:44:20",
    "total": 15.715,
    "used": 13.22,
    "free": 2.495,
    "cache": 0.0
  },
  {
    "timestamp": "2026-03-27 19:44:25",
    "total": 15.715,
    "used": 13.078,
    "free": 2.637,
    "cache": 0.0
  },
  {
    "timestamp": "2026-03-27 19:44:28",
    "total": 15.715,
    "used": 13.079,
    "free": 2.636,
    "cache": 0.0
  },
  {
    "timestamp": "2026-03-27 19:44:30",
    "total": 15.715,
    "used": 13.076,
    "free": 2.639,
    "cache": 0.0
  },
  {
    "timestamp": "2026-03-27 19:44:35",
    "total": 15.715,
    "used": 13.043,
    "free": 2.671,
    "cache": 0.0
  },
  {
    "timestamp": "2026-03-27 19:44:40",
    "total": 15.715,
    "used": 13.056,
    "free": 2.659,
    "cache": 0.0
  },
  {
    "timestamp": "2026-03-27 19:44:45",
    "total": 15.715,
    "used": 13.127,
    "free": 2.588,
    "cache": 0.0
  },
  {
    "timestamp": "2026-03-27 19:44:50",
    "total": 15.715,
    "used": 13.121,
    "free": 2.594,
    "cache": 0.0
  },
  {
    "timestamp": "2026-03-27 19:44:55",
    "total": 15.715,
    "used": 13.119,
    "free": 2.596,
    "cache": 0.0
  },
  {
    "timestamp": "2026-03-27 19:45:00",
    "total": 15.715,
    "used": 13.119,
    "free": 2.596,
    "cache": 0.0
  },
  {
    "timestamp": "2026-03-27 19:45:06",
    "total": 15.715,
    "used": 13.108,
    "free": 2.607,
    "cache": 0.0
  },
  {
    "timestamp": "2026-03-27 19:45:11",
    "total": 15.715,
    "used": 13.12,
    "free": 2.595,
    "cache": 0.0
  }
]